consoleword.py
consoleword-1.0.0.dist-info/WHEEL
consoleword-1.0.0.dist-info/METADATA
consoleword-1.0.0.dist-info/RECORD
